fourbody/__init__.py
fourbody/boosts.py
fourbody/param.py
fourbody/util.py
fourbody-0.4.dist-info/LICENSE
fourbody-0.4.dist-info/METADATA
fourbody-0.4.dist-info/WHEEL
fourbody-0.4.dist-info/top_level.txt
fourbody-0.4.dist-info/RECORD
